AUTHORS
COPYING
LICENSE
MANIFEST.in
README.rst
setup.py
bin/fades
bin/fades.cmd
fades/__init__.py
fades/__main__.py
fades/_version.py
fades/cache.py
fades/envbuilder.py
fades/file_options.py
fades/helpers.py
fades/logger.py
fades/main.py
fades/multiplatform.py
fades/parsing.py
fades/pipmanager.py
fades/pkgnamesdb.py
fades.egg-info/PKG-INFO
fades.egg-info/SOURCES.txt
fades.egg-info/dependency_links.txt
fades.egg-info/requires.txt
fades.egg-info/top_level.txt
man/fades.1