Metadata-Version: 2.1
Name: fades
Version: 9.0.2
Summary: A system that automatically handles the virtualenvs in the cases normally found when writing scripts and simple programs, and even helps to administer big projects.
Home-page: https://github.com/PyAr/fades
Download-URL: https://github.com/PyAr/fades/releases
Author: Facundo Batista, Nicolás Demarchi
Author-email: facundo@taniquetil.com.ar, mail@gilgamezh.me
License: GPL-3
Keywords: virtualenv utils utility scripts
Platform: UNKNOWN
Classifier: Development Status :: 5 - Production/Stable
Classifier: Environment :: Console
Classifier: Intended Audience :: Developers
Classifier: Intended Audience :: System Administrators
Classifier: License :: OSI Approved :: GNU General Public License (GPL)
Classifier: License :: OSI Approved :: GNU General Public License v3 (GPLv3)
Classifier: License :: OSI Approved :: GNU General Public License v3 or later (GPLv3+)
Classifier: Natural Language :: English
Classifier: Natural Language :: Spanish
Classifier: Operating System :: MacOS
Classifier: Operating System :: MacOS :: MacOS X
Classifier: Operating System :: Microsoft
Classifier: Operating System :: Microsoft :: Windows
Classifier: Operating System :: POSIX
Classifier: Operating System :: POSIX :: Linux
Classifier: Programming Language :: Python
Classifier: Programming Language :: Python :: 3
Classifier: Programming Language :: Python :: 3 :: Only
Classifier: Programming Language :: Python :: 3.3
Classifier: Programming Language :: Python :: 3.4
Classifier: Programming Language :: Python :: 3.5
Classifier: Programming Language :: Python :: 3.6
Classifier: Programming Language :: Python :: Implementation
Classifier: Programming Language :: Python :: Implementation :: CPython
Classifier: Topic :: Software Development
Classifier: Topic :: Utilities
Requires-Python: >=3.3
Provides-Extra: pyxdg
Provides-Extra: virtualenv
Provides-Extra: setuptools
License-File: LICENSE
License-File: COPYING
License-File: AUTHORS
